vinted_scraper/__init__.py
vinted_scraper/agents.json
vinted_scraper/utils.py
vinted_scraper/vintedScraper.py
vinted_scraper/vintedWrapper.py
vinted_scraper/models/__init__.py
vinted_scraper/models/vintedBrand.py
vinted_scraper/models/vintedBundleDiscount.py
vinted_scraper/models/vintedHighResolution.py
vinted_scraper/models/vintedImage.py
vinted_scraper/models/vintedItem.py
vinted_scraper/models/vintedMedia.py
vinted_scraper/models/vintedPaymentMethod.py
vinted_scraper/models/vintedUser.py
vinted_scraper-2.3.2.dist-info/METADATA
vinted_scraper-2.3.2.dist-info/WHEEL
vinted_scraper-2.3.2.dist-info/licenses/LICENSE
vinted_scraper-2.3.2.dist-info/RECORD
