Metadata-Version: 2.4
Name: vinted_scraper
Version: 2.3.2
Summary: A very simple Python package that scrapes the Vinted website to retrieve information about its items.
Project-URL: Changelog, https://github.com/Giglium/vinted_scraper/releases
Project-URL: Documentation, https://github.com/Giglium/vinted_scraper
Project-URL: Homepage, https://github.com/Giglium/vinted_scraper
Project-URL: Issues, https://github.com/Giglium/vinted_scraper/issues
Project-URL: Source, https://github.com/Giglium/vinted_scraper
Author: Giglium
License: MIT License
License-File: LICENSE
Classifier: Development Status :: 5 - Production/Stable
Classifier: Intended Audience :: Education
Classifier: License :: OSI Approved :: MIT License
Classifier: Operating System :: OS Independent
Classifier: Programming Language :: Python :: 3
Classifier: Programming Language :: Python :: 3.6
Classifier: Programming Language :: Python :: 3.7
Classifier: Programming Language :: Python :: 3.8
Classifier: Programming Language :: Python :: 3.9
Classifier: Programming Language :: Python :: 3.10
Classifier: Programming Language :: Python :: 3.11
Classifier: Programming Language :: Python :: 3.12
Requires-Python: >=3.6
Requires-Dist: deprecated
Requires-Dist: requests
